fileuploader/AuthError.py
fileuploader/UploadResponse.py
fileuploader/__init__.py
fileuploader/exceptions.py
fileuploader/group.py
fileuploader/user.py
fileuploader-0.1.3.6.dist-info/METADATA
fileuploader-0.1.3.6.dist-info/WHEEL
fileuploader-0.1.3.6.dist-info/top_level.txt
fileuploader-0.1.3.6.dist-info/RECORD
