Metadata-Version: 2.1
Name: fileuploader
Version: 0.1.3.6
Summary: Package for working with the API fu.andcool.ru
Home-page: https://github.com/Andcool-Systems/FileUploader-python
Author: AndcoolSystems
Author-email: main@andcool.ru
License: GPL-3.0 license
Requires-Dist: aiohttp
